getmcp/__init__.py
getmcp/__main__.py
getmcp/cli.py
getmcp/client.py
getmcp-0.1.1.dist-info/METADATA
getmcp-0.1.1.dist-info/WHEEL
getmcp-0.1.1.dist-info/entry_points.txt
getmcp-0.1.1.dist-info/top_level.txt
getmcp-0.1.1.dist-info/RECORD
