Metadata-Version: 2.4
Name: getmcp
Version: 0.1.1
Summary: A tool for searching, pulling, and managing MCP servers
Author-email: Jonathan Wang <jonathan.wang@pathintegral.xyz>
License: MIT
Project-URL: Homepage, https://github.com/pathintegral-xyz/getmcp
Project-URL: Bug Tracker, https://github.com/pathintegral-xyz/getmcp/issues
Classifier: Programming Language :: Python :: 3
Classifier: License :: OSI Approved :: MIT License
Classifier: Operating System :: OS Independent
Requires-Python: >=3.11
Requires-Dist: requests>=2.28.0
